{
  "primary_color": "#3b82f6",
  "on_primary": "#ffffff",
  "bg_color": "#0b1120",
  "card_bg_color": "#0f172a",
  "surface_container_low": "#0f172a",
  "surface_lowest": "#060d1c",
  "surface_high": "#1e293b",
  "surface_highest": "#243040",
  "surface_bright": "#2d3a4f",
  "border_color": "#334155",
  "text_color": "#f8fafc",
  "text_highlight_color": "#ffffff",
  "text_muted_color": "#94a3b8",
  "outline_color": "#64748b",
  "success_color": "#4edea3",
  "secondary_container": "#065f46",
  "danger_color": "#f87171",
  "error_container": "#7f1d1d",
  "warning_color": "#fbbf24",
  "font_header": "'Outfit', sans-serif",
  "font_body": "'Outfit', sans-serif",
  "font_mono": "'JetBrains Mono', monospace",
  "border_radius_sm": "2px",
  "border_radius_md": "4px",
  "border_radius_lg": "8px",
  "border_radius_xl": "12px",
  "spacing_unit": "8px",
  "card_shadow": "none"
}